makwa/__init__.py
makwa/makwa.py
makwa/test.py
makwa-1.0.2.dist-info/DESCRIPTION.rst
makwa-1.0.2.dist-info/METADATA
makwa-1.0.2.dist-info/RECORD
makwa-1.0.2.dist-info/WHEEL
makwa-1.0.2.dist-info/metadata.json
makwa-1.0.2.dist-info/top_level.txt
